intgate/__init__.py
intgate/client.py
intgate/exceptions.py
intgate-1.0.3.dist-info/METADATA
intgate-1.0.3.dist-info/WHEEL
intgate-1.0.3.dist-info/top_level.txt
intgate-1.0.3.dist-info/RECORD
